c8connector/__init__.py
c8connector/util/__init__.py
c8connector-0.0.32.dist-info/entry_points.txt
c8connector-0.0.32.dist-info/LICENSE
c8connector-0.0.32.dist-info/WHEEL
c8connector-0.0.32.dist-info/METADATA
c8connector-0.0.32.dist-info/RECORD
