Metadata-Version: 2.1
Name: c8connector
Version: 0.0.32
Summary: C8 Connector Interface
License: Apache-2.0
Keywords: ELT,Connectors,Workflows,Macrometa
Author: Macrometa
Author-email: info@macrometa.com
Requires-Python: >=3.8.1,<3.11
Classifier: License :: OSI Approved :: Apache Software License
Classifier: Operating System :: OS Independent
Classifier: Programming Language :: Python :: 3
Classifier: Programming Language :: Python :: 3.9
Classifier: Programming Language :: Python :: 3.10
Classifier: Programming Language :: Python :: 3 :: Only
Classifier: Programming Language :: Python :: 3.8
Requires-Dist: fastapi (==0.65.1)
Requires-Dist: psycopg2-binary (==2.9.3)
Requires-Dist: uvicorn (==0.18.0)
Project-URL: Bug Tracker, https://github.com/Macrometacorp/c8connector/issues
Project-URL: Homepage, https://www.macrometa.com/
